columbiaviper/.gitignore
columbiaviper/.gitmodules
columbiaviper/LICENSE
columbiaviper/__init__.py
columbiaviper/download_models.sh
columbiaviper/image_patch.py
columbiaviper/main_batch.py
columbiaviper/main_simple.ipynb
columbiaviper/main_simple_lib.py
columbiaviper/requirements.txt
columbiaviper/setup.sh
columbiaviper/setup_env.sh
columbiaviper/teaser.gif
columbiaviper/utils.py
columbiaviper/video_segment.py
columbiaviper/vision_models.py
columbiaviper/vision_processes.py
columbiaviper/base_models/__init__.py
columbiaviper/base_models/inspyrenet/InSPyReNet.py
columbiaviper/base_models/inspyrenet/__init__.py
columbiaviper/base_models/inspyrenet/saliency_transforms.py
columbiaviper/base_models/inspyrenet/backbones/Res2Net_v1b.py
columbiaviper/base_models/inspyrenet/backbones/SwinTransformer.py
columbiaviper/base_models/inspyrenet/modules/attention_module.py
columbiaviper/base_models/inspyrenet/modules/context_module.py
columbiaviper/base_models/inspyrenet/modules/decoder_module.py
columbiaviper/base_models/inspyrenet/modules/layers.py
columbiaviper/base_models/inspyrenet/optim/__init__.py
columbiaviper/base_models/inspyrenet/optim/losses.py
columbiaviper/base_models/inspyrenet/optim/scheduler.py
columbiaviper/base_models/tcl/__init__.py
columbiaviper/base_models/tcl/tcl_config_bert.json
columbiaviper/base_models/tcl/tcl_model_pretrain.py
columbiaviper/base_models/tcl/tcl_tokenization_bert.py
columbiaviper/base_models/tcl/tcl_vit.py
columbiaviper/base_models/tcl/tcl_xbert.py
columbiaviper/base_models/xvlm/config_bert.json
columbiaviper/base_models/xvlm/swin_transformer.py
columbiaviper/base_models/xvlm/vit.py
columbiaviper/base_models/xvlm/xbert.py
columbiaviper/base_models/xvlm/xvlm.py
columbiaviper/data/queries.csv
columbiaviper/datasets/__init__.py
columbiaviper/datasets/dataset.py
columbiaviper/prompts/api.prompt
columbiaviper/prompts/chatapi.prompt
columbiaviper/prompts/fixed_code/blip2.prompt
columbiaviper/prompts/gpt3/gpt3_qa.txt
columbiaviper-0.0.5.dist-info/METADATA
columbiaviper-0.0.5.dist-info/WHEEL
columbiaviper-0.0.5.dist-info/RECORD
